oracle_object_mapping/__init__.py
oracle_object_mapping/fields.py
oracle_object_mapping/objects.py
oracle_object_mapping/utils.py
oracle_object_mapping-1.0.0.dev2.dist-info/LICENSE.txt
oracle_object_mapping-1.0.0.dev2.dist-info/METADATA
oracle_object_mapping-1.0.0.dev2.dist-info/WHEEL
oracle_object_mapping-1.0.0.dev2.dist-info/top_level.txt
oracle_object_mapping-1.0.0.dev2.dist-info/RECORD
