Metadata-Version: 2.1
Name: oracle-object-mapping
Version: 1.0.0.dev2
Summary: Oracle Object Mapping.
Home-page: https://github.com/domingues/oracle-object-mapping
Author: Fábio Domingues
Author-email: fabio.a.domingues@gmail.com
License: MIT
Platform: UNKNOWN
Classifier: Programming Language :: Python :: 3
Classifier: License :: OSI Approved :: MIT License
Classifier: Topic :: Database
Requires-Python: >=3.7
Requires-Dist: cx-Oracle
Provides-Extra: lint
Requires-Dist: flake8 ; extra == 'lint'
Requires-Dist: flake8-broken-line ; extra == 'lint'
Requires-Dist: flake8-bugbear ; extra == 'lint'
Requires-Dist: flake8-builtins ; extra == 'lint'
Requires-Dist: flake8-commas ; extra == 'lint'
Requires-Dist: flake8-docstrings ; extra == 'lint'
Requires-Dist: flake8-import-order ; extra == 'lint'
Requires-Dist: flake8-pep3101 ; extra == 'lint'
Requires-Dist: flake8-quotes ; extra == 'lint'
Requires-Dist: flake8-rst-docstrings ; extra == 'lint'
Requires-Dist: flake8-string-format ; extra == 'lint'
Requires-Dist: mypy ; extra == 'lint'
